odoo/addons/pos_reuse_pricelist/README.rst
odoo/addons/pos_reuse_pricelist/__manifest__.py
odoo/addons/pos_reuse_pricelist/readme/DESCRIPTION.rst
odoo/addons/pos_reuse_pricelist/static/description/icon.png
odoo/addons/pos_reuse_pricelist/static/description/index.html
odoo/addons/pos_reuse_pricelist/static/src/js/models.js
odoo/addons/pos_reuse_pricelist/views/pos_assets.xml
odoo14_addon_pos_reuse_pricelist-14.0.1.0.1.dist-info/METADATA
odoo14_addon_pos_reuse_pricelist-14.0.1.0.1.dist-info/WHEEL
odoo14_addon_pos_reuse_pricelist-14.0.1.0.1.dist-info/top_level.txt
odoo14_addon_pos_reuse_pricelist-14.0.1.0.1.dist-info/RECORD
